automl_infrastructure/__init__.py
automl_infrastructure/classifiers/__init__.py
automl_infrastructure/classifiers/base.py
automl_infrastructure/classifiers/ensemble_classifier.py
automl_infrastructure/classifiers/adapters/__init__.py
automl_infrastructure/classifiers/adapters/keras_classifier.py
automl_infrastructure/classifiers/adapters/sklearn.py
automl_infrastructure/experiment/__init__.py
automl_infrastructure/experiment/base.py
automl_infrastructure/experiment/params.py
automl_infrastructure/experiment/metrics/__init__.py
automl_infrastructure/experiment/metrics/base.py
automl_infrastructure/experiment/metrics/max_recall_at_precision.py
automl_infrastructure/experiment/metrics/standard_metrics.py
automl_infrastructure/experiment/metrics/threshold_min_precision.py
automl_infrastructure/experiment/metrics/utils.py
automl_infrastructure/experiment/observations/__init__.py
automl_infrastructure/experiment/observations/base.py
automl_infrastructure/experiment/observations/standard_observations.py
automl_infrastructure/interpretation/__init__.py
automl_infrastructure/interpretation/permutation_importance.py
automl_infrastructure/interpretation/lime/__init__.py
automl_infrastructure/interpretation/lime/lime_graph.py
automl_infrastructure/pipeline/__init__.py
automl_infrastructure/pipeline/base.py
automl_infrastructure/pipeline/steps/__init__.py
automl_infrastructure/pipeline/steps/base.py
automl_infrastructure/utils/__init__.py
automl_infrastructure/utils/functions.py
automl_infrastructure/visualization/__init__.py
automl_infrastructure/visualization/base.py
automl_infrastructure/visualization/confusion_matrix.py
automl_infrastructure/visualization/precision_recall_curve.py
automl_infrastructure-0.6.0.dist-info/LICENSE
automl_infrastructure-0.6.0.dist-info/METADATA
automl_infrastructure-0.6.0.dist-info/WHEEL
automl_infrastructure-0.6.0.dist-info/top_level.txt
automl_infrastructure-0.6.0.dist-info/RECORD
