Metadata-Version: 2.1
Name: automl-infrastructure
Version: 0.6.0
Summary: AutoML Infrastructure.
Home-page: UNKNOWN
Author: Barak David
Author-email: UNKNOWN
License: UNKNOWN
Platform: UNKNOWN
Requires-Dist: pandas
Requires-Dist: scikit-learn
Requires-Dist: optuna
Requires-Dist: python-bidi
Requires-Dist: dill
Requires-Dist: numpy
Requires-Dist: scipy
Requires-Dist: matplotlib
